tehran_stocks/__init__.py
tehran_stocks/config/__init__.py
tehran_stocks/config/config.default.yml
tehran_stocks/config/engine.py
tehran_stocks/download/__init__.py
tehran_stocks/download/base.py
tehran_stocks/download/names.py
tehran_stocks/download/price.py
tehran_stocks/initializer.py
tehran_stocks/models/__init__.py
tehran_stocks/models/create.py
tehran_stocks/models/stocks.py
tehran_stocks-2.0.0.dist-info/LICENSE
tehran_stocks-2.0.0.dist-info/METADATA
tehran_stocks-2.0.0.dist-info/WHEEL
tehran_stocks-2.0.0.dist-info/RECORD
