Metadata-Version: 2.1
Name: tehran-stocks
Version: 2.0.0
Summary: Data Downloader for Tehran stock market
Home-page: https://ghodsizadeh.github.io/tehran-stocks/
License: MIT
Author: Mehdi Ghodsizadeh
Author-email: mehdi.ghodsizadeh@gmail.com
Requires-Python: >=3.8.1,<4.0.0
Classifier: License :: OSI Approved :: MIT License
Classifier: Programming Language :: Python :: 3
Classifier: Programming Language :: Python :: 3.9
Classifier: Programming Language :: Python :: 3.10
Classifier: Programming Language :: Python :: 3.11
Requires-Dist: PyYAML (>=6.0,<7.0)
Requires-Dist: SQLAlchemy (>=1.4.28,<2.0.0)
Requires-Dist: aiodns (>=3.0.0,<4.0.0)
Requires-Dist: aiohttp (>=3.8.5,<4.0.0)
Requires-Dist: jalali-pandas (>=0.2.0,<0.3.0)
Requires-Dist: lxml (>=4.8.0,<5.0.0)
Requires-Dist: pandas (>=2.0.3,<3.0.0)
Requires-Dist: requests (>=2.26.0,<3.0.0)
Project-URL: Repository, https://github.com/ghodsizadeh/tehran-stocks.git
